lchat/__init__.py
lchat/__main__.py
lchat/_version.py
lchat/app.py
lchat-0.2.3.dist-info/LICENSE
lchat-0.2.3.dist-info/METADATA
lchat-0.2.3.dist-info/WHEEL
lchat-0.2.3.dist-info/entry_points.txt
lchat-0.2.3.dist-info/RECORD
