Metadata-Version: 2.1
Name: lchat
Version: 0.2.3
Summary: Hugging Face inference chat CLI client.
Home-page: https://github.com/abdrysdale/lchat
License: GPL-3.0-or-later
Author: Alex Drysdale
Author-email: alexander.drysdale@wales.nhs.uk
Requires-Python: >=3.12,<4.0
Classifier: License :: OSI Approved :: GNU General Public License v3 or later (GPLv3+)
Classifier: Programming Language :: Python :: 3
Classifier: Programming Language :: Python :: 3.12
Requires-Dist: huggingface-hub (>=0.24.5,<0.25.0)
Project-URL: Repository, https://github.com/abdrysdale/lchat
